text_pipeline/Pipeline.py
text_pipeline/Stemmer.py
text_pipeline/TokenFilter.py
text_pipeline/Tokenizer.py
text_pipeline/__init__.py
text_pipeline/unit_tests.py
text_pipeline-1.1.dist-info/METADATA
text_pipeline-1.1.dist-info/RECORD
text_pipeline-1.1.dist-info/WHEEL
text_pipeline-1.1.dist-info/top_level.txt
