Metadata-Version: 2.1
Name: text-pipeline
Version: 1.1
Summary: A module for processing text documents in preparation for various NLP models or other tasks that required cleaned text.
Home-page: UNKNOWN
Author: John Sigmon and Sanjana Kapoor
Author-email: johnsigmon@gmail.com, sanjanakapoor793@gmail.com
License: MIT
Platform: UNKNOWN
Requires-Dist: spacy
Requires-Dist: nltk
